tts_clients/__init__.py
tts_clients/py.typed
tts_clients/elevenlabs/__init__.py
tts_clients/elevenlabs/client.py
tts_clients/elevenlabs/models.py
tts_clients/google/__init__.py
tts_clients/google/client.py
tts_clients/google/models.py
tts_clients/minmax/__init__.py
tts_clients/minmax/client.py
tts_clients/minmax/models.py
tts_clients/openai/__init__.py
tts_clients/openai/client.py
tts_clients/openai/models.py
tts_clients-0.6.0.dist-info/METADATA
tts_clients-0.6.0.dist-info/WHEEL
tts_clients-0.6.0.dist-info/RECORD
