Metadata-Version: 2.4
Name: tts-clients
Version: 0.6.0
Summary: Add your description here
Author-email: neka-nat <nekanat.stock@gmail.com>
Requires-Python: >=3.12
Requires-Dist: elevenlabs>=2.1.0
Requires-Dist: google-genai>=1.16.1
Requires-Dist: httpx>=0.28.1
Requires-Dist: openai>=1.81.0
Requires-Dist: pydantic>=2.11.4
Requires-Dist: pydub>=0.25.1
Requires-Dist: python-dotenv>=1.1.0
